Metadata-Version: 2.4
Name: adafruit-circuitpython-mlx90393
Version: 2.3.8
Summary: CircuitPython driver for the MLX90393 3-axis magnetometer.
Author-email: Adafruit Industries <circuitpython@adafruit.com>
License: MIT
Project-URL: Homepage, https://github.com/adafruit/Adafruit_CircuitPython_MLX90393
Keywords: adafruit,three-axis,magnetometer,magnet,mlx90393,hardware,micropython,circuitpython
Classifier: Intended Audience :: Developers
Classifier: Topic :: Software Development :: Libraries
Classifier: Topic :: Software Development :: Embedded Systems
Classifier: Topic :: System :: Hardware
Classifier: License :: OSI Approved :: MIT License
Classifier: Programming Language :: Python :: 3
License-File: LICENSE
Requires-Dist: Adafruit-Blinka>=7.0.0
Requires-Dist: adafruit-circuitpython-busdevice
Requires-Dist: adafruit-circuitpython-typing
Provides-Extra: optional
Dynamic: license-file
